{
  "intents": [
    {
      "intent": "AMAZON.CancelIntent"
    },
    {
      "intent": "AMAZON.HelpIntent"
    },

    { 
     "intent": "DoneIntent",
    "slots": [
      {
      "name": "Done",
      "type":"DONE_SLOTS"
      }
      ]    
      },
    {
      "intent": "AMAZON.StopIntent"
    },
    {
      "slots": [
       
        {
          "name": "requestNumber",
          "type": "AMAZON.NUMBER"
        },
        {
          "name": "requestedPluralService",
          "type": "SERVICES"
        }
      ],
      "intent": "RequestedPluralServiceIntent"
    },
    {
      "slots": [
        {
          "name": "requestedSingularService",
          "type": "SERVICE"
        }
      ],
      "intent": "RequestSingularServiceIntent"
    },
    {"intent": "ForgotIntent",
    "slots":[
      {
        "name": "itemNeeded",
        "type": "SERVICE"
      },
      {
        "name": "requestNumber",
        "type": "AMAZON.NUMBER"       
      }
      ] 
    },
    //     {
    //   "intent": "FoodServiceIntent",
    //   "slots":[
    //     {
    //       "name":"foodItem",
    //       "type":"LIST_OF_MENU_ITEMS"
    //     }
    //   ]
    // },
    {"intent": "HotelInfoLocationIntent",
    "slots":[
      {
        "name": "amenity",
        "type": "AMENITIES"
      } 
      ] 
    },   
    {"intent": "HotelInfoHoursIntent",
    "slots":[
      {
        "name": "amenity",
        "type": "AMENITIES"
      } 
      ] 
    },
    {
      "slots": [
        {
          "name": "days",
          "type": "AMAZON.NUMBER"
        }
      ],
      "intent": "ExtendStayIntent"
    },
    {
      "intent": "MenuIntent"
    }, 
    {
      "intent": "CheckOutIntent"
    },
    {
      "intent": "CheckOutIntent"
    }
  ]
}